Metadata-Version: 2.1
Name: ptpython
Version: 3.0.29
Summary: Python REPL build on top of prompt_toolkit
Home-page: https://github.com/prompt-toolkit/ptpython
Author: Jonathan Slenders
Project-URL: Bug Tracker, https://github.com/prompt-toolkit/ptpython/issues
Project-URL: Source Code, https://github.com/prompt-toolkit/ptpython
Project-URL: Changelog, https://github.com/prompt-toolkit/ptpython/blob/master/CHANGELOG
Classifier: License :: OSI Approved :: BSD License
Classifier: Programming Language :: Python :: 3
Classifier: Programming Language :: Python :: 3.7
Classifier: Programming Language :: Python :: 3.8
Classifier: Programming Language :: Python :: 3.9
Classifier: Programming Language :: Python :: 3.10
Classifier: Programming Language :: Python :: 3.11
Classifier: Programming Language :: Python :: 3.12
Classifier: Programming Language :: Python :: 3 :: Only
Classifier: Programming Language :: Python
Requires-Python: >=3.7
License-File: LICENSE
Requires-Dist: appdirs
Requires-Dist: importlib_metadata; python_version < "3.8"
Requires-Dist: jedi>=0.16.0
Requires-Dist: prompt_toolkit<3.1.0,>=3.0.43
Requires-Dist: pygments
Provides-Extra: ptipython
Requires-Dist: ipython; extra == "ptipython"
Provides-Extra: all
Requires-Dist: black; extra == "all"
